Quartus Files/Lab 3/Files/sevenseg.v
module sevenseg(
input [3:0] data,
input blank,
input minus, 
output reg [7:0] HEX
);

always @(blank, minus, data[3:0])
casex ({blank, minus, data[3:0]})
  6'b1xxxxx: HEX[7:0] = 8'b11111111;     // blank
  6'b01xxxx: HEX[7:0] = 8'b10111111;     // minus
  6'b001111: HEX[7:0] = 8'b10001110;     // F
  6'b001110: HEX[7:0] = 8'b10000110;     // E
  6'b001101: HEX[7:0] = 8'b10100001;     // D
  6'b001100: HEX[7:0] = 8'b11000110;     // C
  6'b001011: HEX[7:0] = 8'b10000011;     // B
  6'b001010: HEX[7:0] = 8'b10001000;     // A
  6'b001001: HEX[7:0] = 8'b10010000;     // 9
  6'b001000: HEX[7:0] = 8'b10000000;     // 8
  6'b000111: HEX[7:0] = 8'b11111000;     // 7
  6'b000110: HEX[7:0] = 8'b10000010;     // 6
  6'b000101: HEX[7:0] = 8'b10010010;     // 5
  6'b000100: HEX[7:0] = 8'b10011001;     // 4
  6'b000011: HEX[7:0] = 8'b10110000;     // 3
  6'b000010: HEX[7:0] = 8'b10100100;     // 2
  6'b000001: HEX[7:0] = 8'b11111001;     // 1
  6'b000000: HEX[7:0] = 8'b11000000;     // 0  
  default: HEX[7:0] = 8'b11111111;
endcase 

endmodule

Quartus Files/Lab 2/Files/translate.v
module translate(
    input clock,
    input reset_n,
    input [3:0] ones,
    input [3:0] tens,
	 input leap,
    output reg [3:0] month,
    output wire [3:0] day1,
    output wire [3:0] day2
);

reg [6:0] value;
reg [4:0] day;

always @(posedge clock or negedge reset_n)
begin
    if (reset_n == 0)
        value <= 1;
    else
        value <= (10*tens) + ({3'b0,ones});
end

always @(posedge clock)
begin
    if (value < 32)
    begin
        month = 1;
        day = value;
    end
    else if (value < (60 + leap))
    begin
        month = 2;
        day = (value - 31);
    end
    else if (value < (91 + leap))
    begin
        month = 3;
        day = (value - (59 + leap));
    end
    else if (value < (100 + leap))
    begin
        month = 4;
        day = (value - (90 + leap));
    end
    else
    begin
        month = 0;
        day = 0;
        end
end

assign day2 = (day / 10);
assign day1 = (day - (day2*10));

endmodule

Quartus Files/Lab 2/Files/bcd2.v
module bcd2(
    input clock,
    input reset_n,
    output reg [3:0] mod10
);

always @(posedge clock or negedge reset_n)
begin
     if (reset_n == 0)
         mod10 <= 0;
     else if (mod10 != 9)
         mod10 <= mod10 + 1;
     else
         mod10 <= 0;
end

endmodule

Quartus Files/Lab 2/Files/bcd1.v
module bcd1(
    input clock,
    input reset_n,
    output reg [3:0] mod10,
	output reg out
);

always @(posedge clock or negedge reset_n)
begin
	if (reset_n == 0)
	   begin
        mod10 <= 1;
		  out <= 0;
		end
   else if (mod10 != 9)
	   begin
        mod10 <= mod10 + 1;
		  out <= 0;
		end
   else
	   begin
        mod10 <= 0;
		  out <= 1;
		end
end


endmodule

Quartus Files/Lab 2/Files/clkdiv.v
module clkdiv(
    input clockin,
	 input key,
    output clockout
);

reg clock = 0;
reg [24:0] count = 0;
wire [24:0] div = key ? 5_000_000 : 1_000_000; // 5 million and 1 million for 1 Hz and 5 Hz, testbench uses 5 and 1

always @(posedge clockin)
begin
    if (count < div)
        count <= count + 1;
    else if (count == div)
    begin
        clock = ~clock;
        count = 0;
    end
    else
        count = 0;
end

assign clockout = clock;

endmodule

Quartus Files/Lab 2/Files/toggle.v
module toggle(
    input key,
    output value
);
reg val = 0;

always @(posedge key)
begin
    val = ~val;
end

assign value = val;
endmodule

Quartus Files/Lab 2/Files/lab2.v
module lab2(
	 input [9:0] SW,
    input [1:0] KEY,
    input ADC_CLK_10,
    output [7:0] HEX5,
    output [7:0] HEX4,
    output [7:0] HEX3,
    output [7:0] HEX2,
    output [7:0] HEX1,
    output [7:0] HEX0,
    output [9:0] LEDR
);

assign LEDR[9] = SW[9];
assign LEDR[8:2] = 1'b0;

////////////// KEY0 Toggle //////////////

wire toggle;
toggle T1 ( .key(KEY[0]), .value(toggle));
assign LEDR[0] = ~toggle;

////////////// KEY1 Toggle //////////////

wire clktoggle;
toggle T2 ( .key(KEY[1]), .value(clktoggle));

////////////// Divide Clock //////////////

wire clock1;
clkdiv D1 ( .clockin(ADC_CLK_10), .key(~clktoggle), .clockout(clock1));
assign LEDR[1] = clock1;

////////////// Start BCDs & Display Output (1-99) //////////////

wire [3:0] value1;
wire [3:0] value2;
wire over;
reg blank = 1;

always @(posedge over or negedge KEY[0])
begin
	 if (KEY[0] == 0)
		  blank = 1;
	 else if (value2 == 9)
		  blank = 1;
	 else
		  blank = 0;
end

bcd1 B4 ( .clock(clock1), .reset_n(toggle), .mod10(value1), .out(over));
bcd2 B5 ( .clock(over), .reset_n(toggle), .mod10(value2));

sevenseg U5 ( .data(value2), .minus(1'b0), .blank(blank), .HEX(HEX5));
sevenseg U4 ( .data(value1), .minus(1'b0), .blank(1'b0), .HEX(HEX4));

////////////// Translate BCD Output & Display as Month (1-4) and Day (1-31) //////////////

wire [3:0] day1;
wire [3:0] day2;
wire [3:0] month;

translate R1 ( .clock(ADC_CLK_10), .reset_n(toggle), .ones(value1), .tens(value2), .leap(SW[9]), .month(month), .day1(day1), .day2(day2));

sevenseg U3 ( .data(), .minus(1'b0), .blank(1'b1), .HEX(HEX3));
sevenseg U2 ( .data(month), .minus(1'b0), .blank(1'b0), .HEX(HEX2));
sevenseg U1 ( .data(day2), .minus(1'b0), .blank(1'b0), .HEX(HEX1));
sevenseg U0 ( .data(day1), .minus(1'b0), .blank(1'b0), .HEX(HEX0));

endmodule

Quartus Files/Lab 2/Files/tb_lab2.v
// DID YOU CHANGE clkdiv.v line 9? IF NOT, THIS WILL TAKE A LONG TIME TO RUN!

`timescale 1 ns / 100 ps

module tb();

reg [1:0] KEY;
reg [9:0] SW;
reg clock = 0;
wire [7:0] HEX0;
wire [7:0] HEX1;
wire [7:0] HEX2;
wire [7:0] HEX4;
wire [7:0] HEX5;


always
    #1 clock = ~clock;

lab2 DUT
(
    .SW(SW),
    .KEY(KEY),
    .ADC_CLK_10(clock),
    .HEX5(HEX5),
    .HEX4(HEX4),
    .HEX2(HEX2),
    .HEX1(HEX1),
    .HEX0(HEX0)
);

initial
begin
    $dumpfile("out.vcd");
    $dumpvars;
    $display($time, " << Starting Simulation >>");
    $display($time, " << Reset Active >>");
    SW[9] = 0;
    KEY[0] = 1;
    KEY[1] = 1;
    #5 $display($time, " << Reset Inactive >>");
    KEY[0] = 0;
    #1 KEY[0] = 1;
    #2400;
    $display($time, " << Reset Active >>");
    KEY[0] = 0;
    #1 KEY[0] = 1;
    #5 $display($time, " << Reset Inactive, Leap Year >>");
    KEY[0] = 0;
    #1 KEY[0] = 1;
    SW[9] = 1;
    #2400;
    $display($time, " << Reset Active >>");
    KEY[0] = 0;
    SW[9] = 0;
    #1 KEY[0] = 1;
    #5 $display($time, " << Reset Inactive, Fast Clock >>");
    KEY[0] = 0;
    KEY[1] = 0;
    #1 KEY[0] = 1;
    KEY[1] = 1;
    #800;
    $display($time, " << Simulation Complete >>");
    $finish;
end

initial
begin
    $monitor($time, " Clock = %b, Reset Key = %b, Value = %b_%b, Month = %b, Day = %b_%b", clock, KEY[0], HEX5, HEX4, HEX2, HEX1, HEX0);
end

endmodule

Quartus Files/Lab 2/Files/out.vcd
$date
	Wed Nov 06 14:11:05 2019
$end
$version
	Icarus Verilog
$end
$timescale
	100ps
$end
$scope module tb $end
$var wire 8 ! HEX5 [7:0] $end
$var wire 8 " HEX4 [7:0] $end
$var wire 8 # HEX2 [7:0] $end
$var wire 8 $ HEX1 [7:0] $end
$var wire 8 % HEX0 [7:0] $end
$var reg 2 & KEY [1:0] $end
$var reg 10 ' SW [9:0] $end
$var reg 1 ( clock $end
$scope module DUT $end
$var wire 1 ( ADC_CLK_10 $end
$var wire 2 ) KEY [1:0] $end
$var wire 10 * SW [9:0] $end
$var wire 4 + value2 [3:0] $end
$var wire 4 , value1 [3:0] $end
$var wire 1 - toggle $end
$var wire 1 . over $end
$var wire 4 / month [3:0] $end
$var wire 4 0 day2 [3:0] $end
$var wire 4 1 day1 [3:0] $end
$var wire 1 2 clock1 $end
$var wire 1 3 clktoggle $end
$var wire 10 4 LEDR [9:0] $end
$var wire 8 5 HEX5 [7:0] $end
$var wire 8 6 HEX4 [7:0] $end
$var wire 8 7 HEX3 [7:0] $end
$var wire 8 8 HEX2 [7:0] $end
$var wire 8 9 HEX1 [7:0] $end
$var wire 8 : HEX0 [7:0] $end
$var reg 1 ; blank $end
$scope module B4 $end
$var wire 1 - reset_n $end
$var wire 1 2 clock $end
$var reg 4 < mod10 [3:0] $end
$var reg 1 . out $end
$upscope $end
$scope module B5 $end
$var wire 1 . clock $end
$var wire 1 - reset_n $end
$var reg 4 = mod10 [3:0] $end
$upscope $end
$scope module D1 $end
$var wire 1 ( clockin $end
$var wire 1 2 clockout $end
$var wire 1 > key $end
$var wire 25 ? div [24:0] $end
$var reg 1 2 clock $end
$var reg 25 @ count [24:0] $end
$upscope $end
$scope module R1 $end
$var wire 1 ( clock $end
$var wire 1 A leap $end
$var wire 4 B ones [3:0] $end
$var wire 4 C tens [3:0] $end
$var wire 1 - reset_n $end
$var wire 4 D day2 [3:0] $end
$var wire 4 E day1 [3:0] $end
$var reg 5 F day [4:0] $end
$var reg 4 G month [3:0] $end
$var reg 7 H value [6:0] $end
$upscope $end
$scope module T1 $end
$var wire 1 I key $end
$var wire 1 - value $end
$var reg 1 - val $end
$upscope $end
$scope module T2 $end
$var wire 1 J key $end
$var wire 1 3 value $end
$var reg 1 3 val $end
$upscope $end
$scope module U0 $end
$var wire 1 K blank $end
$var wire 4 L data [3:0] $end
$var wire 1 M minus $end
$var reg 8 N HEX [7:0] $end
$upscope $end
$scope module U1 $end
$var wire 1 O blank $end
$var wire 4 P data [3:0] $end
$var wire 1 Q minus $end
$var reg 8 R HEX [7:0] $end
$upscope $end
$scope module U2 $end
$var wire 1 S blank $end
$var wire 4 T data [3:0] $end
$var wire 1 U minus $end
$var reg 8 V HEX [7:0] $end
$upscope $end
$scope module U3 $end
$var wire 1 W blank $end
$var wire 4 X data [3:0] $end
$var wire 1 Y minus $end
$var reg 8 Z HEX [7:0] $end
$upscope $end
$scope module U4 $end
$var wire 1 [ blank $end
$var wire 4 \ data [3:0] $end
$var wire 1 ] minus $end
$var reg 8 ^ HEX [7:0] $end
$upscope $end
$scope module U5 $end
$var wire 1 ; blank $end
$var wire 4 _ data [3:0] $end
$var wire 1 ` minus $end
$var reg 8 a HEX [7:0] $end
$upscope $end
$upscope $end
$upscope $end
$enddefinitions $end
#0
$dumpvars
b11111111 a
0`
b0 _
b11111001 ^
0]
b1 \
0[
b11111111 Z
0Y
bz X
1W
b10001110 V
0U
bx T
0S
b10001110 R
0Q
bx P
0O
b10001110 N
0M
bx L
0K
1J
1I
b1 H
bx G
bx F
bx E
bx D
b0 C
b1 B
0A
b0 @
b101 ?
1>
b0 =
b1 <
1;
b10001110 :
b10001110 9
b10001110 8
b11111111 7
b11111001 6
b11111111 5
b1 4
03
02
bx 1
bx 0
bx /
0.
0-
b1 ,
b0 +
b0xxxxxxxxx *
b11 )
0(
b0xxxxxxxxx '
b11 &
b10001110 %
b10001110 $
b10001110 #
b11111001 "
b11111111 !
$end
#10
b1 @
b11111001 %
b11111001 :
b11111001 N
b1 1
b1 E
b1 L
b11000000 $
b11000000 9
b11000000 R
b0 0
b0 D
b0 P
b11111001 #
b11111001 8
b11111001 V
b1 F
b1 /
b1 G
b1 T
1(
#20
0(
#30
b10 @
1(
#40
0(
#50
b11 @
0I
1(
b10 &
b10 )
#60
b0 4
1-
1I
0(
b11 &
b11 )
#70
b100 @
1(
#80
0(
#90
b101 @
1(
#100
0(
#110
b10100100 "
b10100100 6
b10100100 ^
b10 ,
b10 <
b10 B
b10 \
b0 @
b10 4
12
1(
#120
0(
#130
b1 @
b10 H
1(
#140
0(
#150
b10 @
b10100100 %
b10100100 :
b10100100 N
b10 1
b10 E
b10 L
b10 F
1(
#160
0(
#170
b11 @
1(
#180
0(
#190
b100 @
1(
#200
0(
#210
b101 @
1(
#220
0(
#230
b0 @
b0 4
02
1(
#240
0(
#250
b1 @
1(
#260
0(
#270
b10 @
1(
#280
0(
#290
b11 @
1(
#300
0(
#310
b100 @
1(
#320
0(
#330
b101 @
1(
#340
0(
#350
b10110000 "
b10110000 6
b10110000 ^
b11 ,
b11 <
b11 B
b11 \
b0 @
b10 4
12
1(
#360
0(
#370
b1 @
b11 H
1(
#380
0(
#390
b10 @
b10110000 %
b10110000 :
b10110000 N
b11 1
b11 E
b11 L
b11 F
1(
#400
0(
#410
b11 @
1(
#420
0(
#430
b100 @
1(
#440
0(
#450
b101 @
1(
#460
0(
#470
b0 @
b0 4
02
1(
#480
0(
#490
b1 @
1(
#500
0(
#510
b10 @
1(
#520
0(
#530
b11 @
1(
#540
0(
#550
b100 @
1(
#560
0(
#570
b101 @
1(
#580
0(
#590
b10011001 "
b10011001 6
b10011001 ^
b100 ,
b100 <
b100 B
b100 \
b0 @
b10 4
12
1(
#600
0(
#610
b1 @
b100 H
1(
#620
0(
#630
b10 @
b10011001 %
b10011001 :
b10011001 N
b100 1
b100 E
b100 L
b100 F
1(
#640
0(
#650
b11 @
1(
#660
0(
#670
b100 @
1(
#680
0(
#690
b101 @
1(
#700
0(
#710
b0 @
b0 4
02
1(
#720
0(
#730
b1 @
1(
#740
0(
#750
b10 @
1(
#760
0(
#770
b11 @
1(
#780
0(
#790
b100 @
1(
#800
0(
#810
b101 @
1(
#820
0(
#830
b10010010 "
b10010010 6
b10010010 ^
b101 ,
b101 <
b101 B
b101 \
b0 @
b10 4
12
1(
#840
0(
#850
b1 @
b101 H
1(
#860
0(
#870
b10 @
b10010010 %
b10010010 :
b10010010 N
b101 1
b101 E
b101 L
b101 F
1(
#880
0(
#890
b11 @
1(
#900
0(
#910
b100 @
1(
#920
0(
#930
b101 @
1(
#940
0(
#950
b0 @
b0 4
02
1(
#960
0(
#970
b1 @
1(
#980
0(
#990
b10 @
1(
#1000
0(
#1010
b11 @
1(
#1020
0(
#1030
b100 @
1(
#1040
0(
#1050
b101 @
1(
#1060
0(
#1070
b10000010 "
b10000010 6
b10000010 ^
b110 ,
b110 <
b110 B
b110 \
b0 @
b10 4
12
1(
#1080
0(
#1090
b1 @
b110 H
1(
#1100
0(
#1110
b10 @
b10000010 %
b10000010 :
b10000010 N
b110 1
b110 E
b110 L
b110 F
1(
#1120
0(
#1130
b11 @
1(
#1140
0(
#1150
b100 @
1(
#1160
0(
#1170
b101 @
1(
#1180
0(
#1190
b0 @
b0 4
02
1(
#1200
0(
#1210
b1 @
1(
#1220
0(
#1230
b10 @
1(
#1240
0(
#1250
b11 @
1(
#1260
0(
#1270
b100 @
1(
#1280
0(
#1290
b101 @
1(
#1300
0(
#1310
b11111000 "
b11111000 6
b11111000 ^
b111 ,
b111 <
b111 B
b111 \
b0 @
b10 4
12
1(
#1320
0(
#1330
b1 @
b111 H
1(
#1340
0(
#1350
b10 @
b11111000 %
b11111000 :
b11111000 N
b111 1
b111 E
b111 L
b111 F
1(
#1360
0(
#1370
b11 @
1(
#1380
0(
#1390
b100 @
1(
#1400
0(
#1410
b101 @
1(
#1420
0(
#1430
b0 @
b0 4
02
1(
#1440
0(
#1450
b1 @
1(
#1460
0(
#1470
b10 @
1(
#1480
0(
#1490
b11 @
1(
#1500
0(
#1510
b100 @
1(
#1520
0(
#1530
b101 @
1(
#1540
0(
#1550
b10000000 "
b10000000 6
b10000000 ^
b1000 ,
b1000 <
b1000 B
b1000 \
b0 @
b10 4
12
1(
#1560
0(
#1570
b1 @
b1000 H
1(
#1580
0(
#1590
b10 @
b10000000 %
b10000000 :
b10000000 N
b1000 1
b1000 E
b1000 L
b1000 F
1(
#1600
0(
#1610
b11 @
1(
#1620
0(
#1630
b100 @
1(
#1640
0(
#1650
b101 @
1(
#1660
0(
#1670
b0 @
b0 4
02
1(
#1680
0(
#1690
b1 @
1(
#1700
0(
#1710
b10 @
1(
#1720
0(
#1730
b11 @
1(
#1740
0(
#1750
b100 @
1(
#1760
0(
#1770
b101 @
1(
#1780
0(
#1790
b10010000 "
b10010000 6
b10010000 ^
b1001 ,
b1001 <
b1001 B
b1001 \
b0 @
b10 4
12
1(
#1800
0(
#1810
b1 @
b1001 H
1(
#1820
0(
#1830
b10 @
b10010000 %
b10010000 :
b10010000 N
b1001 1
b1001 E
b1001 L
b1001 F
1(
#1840
0(
#1850
b11 @
1(
#1860
0(
#1870
b100 @
1(
#1880
0(
#1890
b101 @
1(
#1900
0(
#1910
b0 @
b0 4
02
1(
#1920
0(
#1930
b1 @
1(
#1940
0(
#1950
b10 @
1(
#1960
0(
#1970
b11 @
1(
#1980
0(
#1990
b100 @
1(
#2000
0(
#2010
b101 @
1(
#2020
0(
#2030
b1 +
b1 =
b1 C
b1 _
b11111001 !
b11111001 5
b11111001 a
0;
b11000000 "
b11000000 6
b11000000 ^
1.
b0 ,
b0 <
b0 B
b0 \
b0 @
b10 4
12
1(
#2040
0(
#2050
b1 @
b1010 H
1(
#2060
0(
#2070
b10 @
b11111001 $
b11111001 9
b11111001 R
b11000000 %
b11000000 :
b11000000 N
b1 0
b1 D
b1 P
b0 1
b0 E
b0 L
b1010 F
1(
#2080
0(
#2090
b11 @
1(
#2100
0(
#2110
b100 @
1(
#2120
0(
#2130
b101 @
1(
#2140
0(
#2150
b0 @
b0 4
02
1(
#2160
0(
#2170
b1 @
1(
#2180
0(
#2190
b10 @
1(
#2200
0(
#2210
b11 @
1(
#2220
0(
#2230
b100 @
1(
#2240
0(
#2250
b101 @
1(
#2260
0(
#2270
b11111001 "
b11111001 6
b11111001 ^
0.
b1 ,
b1 <
b1 B
b1 \
b0 @
b10 4
12
1(
#2280
0(
#2290
b1 @
b1011 H
1(
#2300
0(
#2310
b10 @
b11111001 %
b11111001 :
b11111001 N
b1 1
b1 E
b1 L
b1011 F
1(
#2320
0(
#2330
b11 @
1(
#2340
0(
#2350
b100 @
1(
#2360
0(
#2370
b101 @
1(
#2380
0(
#2390
b0 @
b0 4
02
1(
#2400
0(
#2410
b1 @
1(
#2420
0(
#2430
b10 @
1(
#2440
0(
#2450
b11 @
1(
#2460
0(
#2470
b100 @
1(
#2480
0(
#2490
b101 @
1(
#2500
0(
#2510
b10100100 "
b10100100 6
b10100100 ^
b10 ,
b10 <
b10 B
b10 \
b0 @
b10 4
12
1(
#2520
0(
#2530
b1 @
b1100 H
1(
#2540
0(
#2550
b10 @
b10100100 %
b10100100 :
b10100100 N
b10 1
b10 E
b10 L
b1100 F
1(
#2560
0(
#2570
b11 @
1(
#2580
0(
#2590
b100 @
1(
#2600
0(
#2610
b101 @
1(
#2620
0(
#2630
b0 @
b0 4
02
1(
#2640
0(
#2650
b1 @
1(
#2660
0(
#2670
b10 @
1(
#2680
0(
#2690
b11 @
1(
#2700
0(
#2710
b100 @
1(
#2720
0(
#2730
b101 @
1(
#2740
0(
#2750
b10110000 "
b10110000 6
b10110000 ^
b11 ,
b11 <
b11 B
b11 \
b0 @
b10 4
12
1(
#2760
0(
#2770
b1 @
b1101 H
1(
#2780
0(
#2790
b10 @
b10110000 %
b10110000 :
b10110000 N
b11 1
b11 E
b11 L
b1101 F
1(
#2800
0(
#2810
b11 @
1(
#2820
0(
#2830
b100 @
1(
#2840
0(
#2850
b101 @
1(
#2860
0(
#2870
b0 @
b0 4
02
1(
#2880
0(
#2890
b1 @
1(
#2900
0(
#2910
b10 @
1(
#2920
0(
#2930
b11 @
1(
#2940
0(
#2950
b100 @
1(
#2960
0(
#2970
b101 @
1(
#2980
0(
#2990
b10011001 "
b10011001 6
b10011001 ^
b100 ,
b100 <
b100 B
b100 \
b0 @
b10 4
12
1(
#3000
0(
#3010
b1 @
b1110 H
1(
#3020
0(
#3030
b10 @
b10011001 %
b10011001 :
b10011001 N
b100 1
b100 E
b100 L
b1110 F
1(
#3040
0(
#3050
b11 @
1(
#3060
0(
#3070
b100 @
1(
#3080
0(
#3090
b101 @
1(
#3100
0(
#3110
b0 @
b0 4
02
1(
#3120
0(
#3130
b1 @
1(
#3140
0(
#3150
b10 @
1(
#3160
0(
#3170
b11 @
1(
#3180
0(
#3190
b100 @
1(
#3200
0(
#3210
b101 @
1(
#3220
0(
#3230
b10010010 "
b10010010 6
b10010010 ^
b101 ,
b101 <
b101 B
b101 \
b0 @
b10 4
12
1(
#3240
0(
#3250
b1 @
b1111 H
1(
#3260
0(
#3270
b10 @
b10010010 %
b10010010 :
b10010010 N
b101 1
b101 E
b101 L
b1111 F
1(
#3280
0(
#3290
b11 @
1(
#3300
0(
#3310
b100 @
1(
#3320
0(
#3330
b101 @
1(
#3340
0(
#3350
b0 @
b0 4
02
1(
#3360
0(
#3370
b1 @
1(
#3380
0(
#3390
b10 @
1(
#3400
0(
#3410
b11 @
1(
#3420
0(
#3430
b100 @
1(
#3440
0(
#3450
b101 @
1(
#3460
0(
#3470
b10000010 "
b10000010 6
b10000010 ^
b110 ,
b110 <
b110 B
b110 \
b0 @
b10 4
12
1(
#3480
0(
#3490
b1 @
b10000 H
1(
#3500
0(
#3510
b10 @
b10000010 %
b10000010 :
b10000010 N
b110 1
b110 E
b110 L
b10000 F
1(
#3520
0(
#3530
b11 @
1(
#3540
0(
#3550
b100 @
1(
#3560
0(
#3570
b101 @
1(
#3580
0(
#3590
b0 @
b0 4
02
1(
#3600
0(
#3610
b1 @
1(
#3620
0(
#3630
b10 @
1(
#3640
0(
#3650
b11 @
1(
#3660
0(
#3670
b100 @
1(
#3680
0(
#3690
b101 @
1(
#3700
0(
#3710
b11111000 "
b11111000 6
b11111000 ^
b111 ,
b111 <
b111 B
b111 \
b0 @
b10 4
12
1(
#3720
0(
#3730
b1 @
b10001 H
1(
#3740
0(
#3750
b10 @
b11111000 %
b11111000 :
b11111000 N
b111 1
b111 E
b111 L
b10001 F
1(
#3760
0(
#3770
b11 @
1(
#3780
0(
#3790
b100 @
1(
#3800
0(
#3810
b101 @
1(
#3820
0(
#3830
b0 @
b0 4
02
1(
#3840
0(
#3850
b1 @
1(
#3860
0(
#3870
b10 @
1(
#3880
0(
#3890
b11 @
1(
#3900
0(
#3910
b100 @
1(
#3920
0(
#3930
b101 @
1(
#3940
0(
#3950
b10000000 "
b10000000 6
b10000000 ^
b1000 ,
b1000 <
b1000 B
b1000 \
b0 @
b10 4
12
1(
#3960
0(
#3970
b1 @
b10010 H
1(
#3980
0(
#3990
b10 @
b10000000 %
b10000000 :
b10000000 N
b1000 1
b1000 E
b1000 L
b10010 F
1(
#4000
0(
#4010
b11 @
1(
#4020
0(
#4030
b100 @
1(
#4040
0(
#4050
b101 @
1(
#4060
0(
#4070
b0 @
b0 4
02
1(
#4080
0(
#4090
b1 @
1(
#4100
0(
#4110
b10 @
1(
#4120
0(
#4130
b11 @
1(
#4140
0(
#4150
b100 @
1(
#4160
0(
#4170
b101 @
1(
#4180
0(
#4190
b10010000 "
b10010000 6
b10010000 ^
b1001 ,
b1001 <
b1001 B
b1001 \
b0 @
b10 4
12
1(
#4200
0(
#4210
b1 @
b10011 H
1(
#4220
0(
#4230
b10 @
b10010000 %
b10010000 :
b10010000 N
b1001 1
b1001 E
b1001 L
b10011 F
1(
#4240
0(
#4250
b11 @
1(
#4260
0(
#4270
b100 @
1(
#4280
0(
#4290
b101 @
1(
#4300
0(
#4310
b0 @
b0 4
02
1(
#4320
0(
#4330
b1 @
1(
#4340
0(
#4350
b10 @
1(
#4360
0(
#4370
b11 @
1(
#4380
0(
#4390
b100 @
1(
#4400
0(
#4410
b101 @
1(
#4420
0(
#4430
b10100100 !
b10100100 5
b10100100 a
b10 +
b10 =
b10 C
b10 _
b11000000 "
b11000000 6
b11000000 ^
1.
b0 ,
b0 <
b0 B
b0 \
b0 @
b10 4
12
1(
#4440
0(
#4450
b1 @
b10100 H
1(
#4460
0(
#4470
b10 @
b10100100 $
b10100100 9
b10100100 R
b11000000 %
b11000000 :
b11000000 N
b10 0
b10 D
b10 P
b0 1
b0 E
b0 L
b10100 F
1(
#4480
0(
#4490
b11 @
1(
#4500
0(
#4510
b100 @
1(
#4520
0(
#4530
b101 @
1(
#4540
0(
#4550
b0 @
b0 4
02
1(
#4560
0(
#4570
b1 @
1(
#4580
0(
#4590
b10 @
1(
#4600
0(
#4610
b11 @
1(
#4620
0(
#4630
b100 @
1(
#4640
0(
#4650
b101 @
1(
#4660
0(
#4670
b11111001 "
b11111001 6
b11111001 ^
0.
b1 ,
b1 <
b1 B
b1 \
b0 @
b10 4
12
1(
#4680
0(
#4690
b1 @
b10101 H
1(
#4700
0(
#4710
b10 @
b11111001 %
b11111001 :
b11111001 N
b1 1
b1 E
b1 L
b10101 F
1(
#4720
0(
#4730
b11 @
1(
#4740
0(
#4750
b100 @
1(
#4760
0(
#4770
b101 @
1(
#4780
0(
#4790
b0 @
b0 4
02
1(
#4800
0(
#4810
b1 @
1(
#4820
0(
#4830
b10 @
1(
#4840
0(
#4850
b11 @
1(
#4860
0(
#4870
b100 @
1(
#4880
0(
#4890
b101 @
1(
#4900
0(
#4910
b10100100 "
b10100100 6
b10100100 ^
b10 ,
b10 <
b10 B
b10 \
b0 @
b10 4
12
1(
#4920
0(
#4930
b1 @
b10110 H
1(
#4940
0(
#4950
b10 @
b10100100 %
b10100100 :
b10100100 N
b10 1
b10 E
b10 L
b10110 F
1(
#4960
0(
#4970
b11 @
1(
#4980
0(
#4990
b100 @
1(
#5000
0(
#5010
b101 @
1(
#5020
0(
#5030
b0 @
b0 4
02
1(
#5040
0(
#5050
b1 @
1(
#5060
0(
#5070
b10 @
1(
#5080
0(
#5090
b11 @
1(
#5100
0(
#5110
b100 @
1(
#5120
0(
#5130
b101 @
1(
#5140
0(
#5150
b10110000 "
b10110000 6
b10110000 ^
b11 ,
b11 <
b11 B
b11 \
b0 @
b10 4
12
1(
#5160
0(
#5170
b1 @
b10111 H
1(
#5180
0(
#5190
b10 @
b10110000 %
b10110000 :
b10110000 N
b11 1
b11 E
b11 L
b10111 F
1(
#5200
0(
#5210
b11 @
1(
#5220
0(
#5230
b100 @
1(
#5240
0(
#5250
b101 @
1(
#5260
0(
#5270
b0 @
b0 4
02
1(
#5280
0(
#5290
b1 @
1(
#5300
0(
#5310
b10 @
1(
#5320
0(
#5330
b11 @
1(
#5340
0(
#5350
b100 @
1(
#5360
0(
#5370
b101 @
1(
#5380
0(
#5390
b10011001 "
b10011001 6
b10011001 ^
b100 ,
b100 <
b100 B
b100 \
b0 @
b10 4
12
1(
#5400
0(
#5410
b1 @
b11000 H
1(
#5420
0(
#5430
b10 @
b10011001 %
b10011001 :
b10011001 N
b100 1
b100 E
b100 L
b11000 F
1(
#5440
0(
#5450
b11 @
1(
#5460
0(
#5470
b100 @
1(
#5480
0(
#5490
b101 @
1(
#5500
0(
#5510
b0 @
b0 4
02
1(
#5520
0(
#5530
b1 @
1(
#5540
0(
#5550
b10 @
1(
#5560
0(
#5570
b11 @
1(
#5580
0(
#5590
b100 @
1(
#5600
0(
#5610
b101 @
1(
#5620
0(
#5630
b10010010 "
b10010010 6
b10010010 ^
b101 ,
b101 <
b101 B
b101 \
b0 @
b10 4
12
1(
#5640
0(
#5650
b1 @
b11001 H
1(
#5660
0(
#5670
b10 @
b10010010 %
b10010010 :
b10010010 N
b101 1
b101 E
b101 L
b11001 F
1(
#5680
0(
#5690
b11 @
1(
#5700
0(
#5710
b100 @
1(
#5720
0(
#5730
b101 @
1(
#5740
0(
#5750
b0 @
b0 4
02
1(
#5760
0(
#5770
b1 @
1(
#5780
0(
#5790
b10 @
1(
#5800
0(
#5810
b11 @
1(
#5820
0(
#5830
b100 @
1(
#5840
0(
#5850
b101 @
1(
#5860
0(
#5870
b10000010 "
b10000010 6
b10000010 ^
b110 ,
b110 <
b110 B
b110 \
b0 @
b10 4
12
1(
#5880
0(
#5890
b1 @
b11010 H
1(
#5900
0(
#5910
b10 @
b10000010 %
b10000010 :
b10000010 N
b110 1
b110 E
b110 L
b11010 F
1(
#5920
0(
#5930
b11 @
1(
#5940
0(
#5950
b100 @
1(
#5960
0(
#5970
b101 @
1(
#5980
0(
#5990
b0 @
b0 4
02
1(
#6000
0(
#6010
b1 @
1(
#6020
0(
#6030
b10 @
1(
#6040
0(
#6050
b11 @
1(
#6060
0(
#6070
b100 @
1(
#6080
0(
#6090
b101 @
1(
#6100
0(
#6110
b11111000 "
b11111000 6
b11111000 ^
b111 ,
b111 <
b111 B
b111 \
b0 @
b10 4
12
1(
#6120
0(
#6130
b1 @
b11011 H
1(
#6140
0(
#6150
b10 @
b11111000 %
b11111000 :
b11111000 N
b111 1
b111 E
b111 L
b11011 F
1(
#6160
0(
#6170
b11 @
1(
#6180
0(
#6190
b100 @
1(
#6200
0(
#6210
b101 @
1(
#6220
0(
#6230
b0 @
b0 4
02
1(
#6240
0(
#6250
b1 @
1(
#6260
0(
#6270
b10 @
1(
#6280
0(
#6290
b11 @
1(
#6300
0(
#6310
b100 @
1(
#6320
0(
#6330
b101 @
1(
#6340
0(
#6350
b10000000 "
b10000000 6
b10000000 ^
b1000 ,
b1000 <
b1000 B
b1000 \
b0 @
b10 4
12
1(
#6360
0(
#6370
b1 @
b11100 H
1(
#6380
0(
#6390
b10 @
b10000000 %
b10000000 :
b10000000 N
b1000 1
b1000 E
b1000 L
b11100 F
1(
#6400
0(
#6410
b11 @
1(
#6420
0(
#6430
b100 @
1(
#6440
0(
#6450
b101 @
1(
#6460
0(
#6470
b0 @
b0 4
02
1(
#6480
0(
#6490
b1 @
1(
#6500
0(
#6510
b10 @
1(
#6520
0(
#6530
b11 @
1(
#6540
0(
#6550
b100 @
1(
#6560
0(
#6570
b101 @
1(
#6580
0(
